{"skeleton":{"hash":"E7wBJ1lZtDoABjp/MLACR9zcCOs","spine":"3.8.99","x":-47,"y":-23.38,"width":94,"height":102,"images":"./images/","audio":""},"bones":[{"name":"root"},{"name":"bone3","parent":"root","x":503.06,"y":11.17}],"slots":[{"name":"zk","bone":"bone3"}],"skins":[{"name":"default","attachments":{"zk":{"001":{"x":0.5,"width":95,"height":96},"002":{"x":0.5,"width":95,"height":96},"003":{"x":0.5,"width":95,"height":96},"004":{"x":0.5,"width":95,"height":96},"005":{"x":0.5,"width":95,"height":96},"006":{"x":0.5,"width":95,"height":96}}}}],"animations":{"animation":{"slots":{"zk":{"color":[{"color":"ffffffd6","curve":"stepped"},{"time":0.1667,"color":"ffffffd6"},{"time":0.2667,"color":"ffffff00"}],"attachment":[{"time":0.1,"name":"003"},{"time":0.1333,"name":"004"},{"time":0.1667,"name":"005"},{"time":0.2,"name":"006"}]}},"bones":{"bone3":{"translate":[{"x":-503.06,"y":-11.17}],"scale":[{"x":1.279,"y":1.279}]}}}}}