{"skeleton":{"hash":"me6ItxyoATn+asxj+/bue5G2fnU","spine":"3.8.99","x":-51.4,"y":-50.72,"width":102.8,"height":102.8,"images":"./images/","audio":"C:/Users/Administrator/Desktop/打爆怪兽/音波炮8"},"bones":[{"name":"root"},{"name":"02chaoshengpao","parent":"root"},{"name":"AE_0","parent":"02chaoshengpao"}],"slots":[{"name":"AE_0","bone":"AE_0","color":"ffffffe4","attachment":"AE_002"}],"skins":[{"name":"default","attachments":{"AE_0":{"AE_000":{"x":-0.34,"y":202.37,"width":57,"height":506},"AE_001":{"x":3.66,"y":202.87,"width":61,"height":493},"AE_002":{"x":3.16,"y":197.37,"width":62,"height":474},"AE_003":{"x":2.66,"y":197.37,"width":55,"height":484},"AE_004":{"x":4.16,"y":202.87,"width":62,"height":505},"AE_005":{"x":4.66,"y":192.87,"width":65,"height":485},"AE_006":{"x":4.16,"y":188.87,"width":66,"height":477},"AE_007":{"x":4.16,"y":225.87,"width":66,"height":465}}}}],"animations":{"animation":{"slots":{"AE_0":{"attachment":[{"name":"AE_000"},{"time":0.0333,"name":"AE_001"},{"time":0.0667,"name":"AE_002"},{"time":0.1,"name":"AE_003"},{"time":0.1333,"name":"AE_004"},{"time":0.1667,"name":"AE_005"},{"time":0.2,"name":"AE_006"},{"time":0.2333,"name":"AE_007"},{"time":0.2667,"name":null}]}}}}}